<ObjectTemplate>
	<ClientId>1183</ClientId>
	<Name>[FF9500]Broodwood Arrow[-]</Name>
	<Hue>851</Hue>
	<SharedStateEntry name="Weight" type="int" value="1"/>
	<ObjectVariableComponent>	
		<StringVariable Name="ResourceType">BroodwoodArrows</StringVariable>
		<StringVariable Name="SingularName">Broodwood Arrow</StringVariable>
		<StringVariable Name="PluralName">Broodwood Arrows</StringVariable>
		<DoubleVariable Name="UnitWeight">0.1</DoubleVariable>
		<DoubleVariable Name="AttackBonus">30</DoubleVariable>
	</ObjectVariableComponent>
	<ScriptEngineComponent>
		<LuaModule Name="stackable"/>
	</ScriptEngineComponent>
</ObjectTemplate>