<ObjectTemplate>
  <Name>[00FF00]Lesser Cure Potion[-]</Name>
	<ClientId>2006</ClientId>
	<ScaleModifier>0.3</ScaleModifier>
	<Color>0xFFFFA31A</Color>
	<SharedStateEntry name="Weight" type="int" value="1"/>
	<ObjectVariableComponent>
		<StringVariable Name="ResourceType">PotionLesserCure</StringVariable>
		<StringVariable Name="PluralName">Lesser Cure Potions</StringVariable>
		<StringVariable Name="ResourceUseSFX">event:/objects/consumables/potion/potion_use</StringVariable>
	</ObjectVariableComponent>
	<ScriptEngineComponent>
		<LuaModule Name="stackable"/>
	</ScriptEngineComponent>
</ObjectTemplate>