<ObjectTemplate>
  <Name>[00FF00]Superior Cure Potion[-]</Name>
	<ClientId>35</ClientId>
	<ScaleModifier>0.75</ScaleModifier>
	<Color>0xFFFFA31A</Color>
	<SharedStateEntry name="Weight" type="int" value="1"/>
	<ObjectVariableComponent>
		<StringVariable Name="ResourceType">PotionSuperiorCure</StringVariable>
		<StringVariable Name="PluralName">Superior Cure Potions</StringVariable>
		<StringVariable Name="ResourceUseSFX">event:/objects/consumables/potion/potion_use</StringVariable>
	</ObjectVariableComponent>
	<ScriptEngineComponent>
		<LuaModule Name="stackable"/>
	</ScriptEngineComponent>
</ObjectTemplate>